README.md
setup.cfg
setup.py
topsis_abhinav_101803411.egg-info/PKG-INFO
topsis_abhinav_101803411.egg-info/SOURCES.txt
topsis_abhinav_101803411.egg-info/dependency_links.txt
topsis_abhinav_101803411.egg-info/entry_points.txt
topsis_abhinav_101803411.egg-info/requires.txt
topsis_abhinav_101803411.egg-info/top_level.txt
topsis_py/topsis.py.py