Metadata-Version: 2.1
Name: topsis-abhinav-101803411
Version: 1.0.3
Summary: A Python package implementing TOPSIS technique.
Home-page: UNKNOWN
Author: Abhinav Narang
Author-email: abhinavnarang000@gmail.com
License: MIT
Keywords: Ranking,Topsis
Platform: UNKNOWN
Classifier: License :: OSI Approved :: MIT License
Classifier: Programming Language :: Python :: 3.7
